isopytools/__init__.py
isopytools/fitutils.py
isopytools/iso2diffpy.py
isopytools/tests/__init__.py
isopytools/tests/tests.py
isopytools-0.0.2.dist-info/AUTHORS.txt
isopytools-0.0.2.dist-info/LICENSE.txt
isopytools-0.0.2.dist-info/METADATA
isopytools-0.0.2.dist-info/WHEEL
isopytools-0.0.2.dist-info/top_level.txt
isopytools-0.0.2.dist-info/RECORD
