Metadata-Version: 2.1
Name: isopytools
Version: 0.0.2
Summary: Tools for working with ISODISTORT output for DiffPy fits
Author-email: Benjamin Frandsen <benfrandsen@byu.edu>
License: Copyright 2023 BENJAMIN ALLEN FRANDSEN
Project-URL: Homepage, https://github.com/FrandsenGroup/isopytools
Project-URL: Issues, https://github.com/FrandsenGroup/isopytools/issues
Classifier: Development Status :: 5 - Production/Stable
Classifier: Environment :: Console
Classifier: Intended Audience :: Developers
Classifier: Intended Audience :: Science/Research
Classifier: License :: OSI Approved :: BSD License
Classifier: Operating System :: MacOS :: MacOS X
Classifier: Operating System :: Microsoft :: Windows
Classifier: Operating System :: POSIX
Classifier: Operating System :: Unix
Classifier: Programming Language :: Python :: 3.7
Classifier: Topic :: Scientific/Engineering :: Physics
Requires-Python: >=3.7
License-File: LICENSE.txt
License-File: AUTHORS.txt
